portformer/__init__.py
portformer/config.py
portformer/errors.py
portformer/__pycache__/__init__.cpython-37.pyc
portformer/__pycache__/__init__.cpython-38.pyc
portformer/__pycache__/config.cpython-37.pyc
portformer/__pycache__/config.cpython-38.pyc
portformer/__pycache__/errors.cpython-38.pyc
portformer/backtest/__init__.py
portformer/breakpoint/__init__.py
portformer/breakpoint/api.py
portformer/breakpoint/__pycache__/__init__.cpython-38.pyc
portformer/breakpoint/__pycache__/api.cpython-38.pyc
portformer/tests/test_config.py
portformer/tests/breakpoint/test_api.py
portformer/tests/breakpoint/__pycache__/test_api.cpython-38-pytest-6.1.2.pyc
portformer/tests/viz/test_main.py
portformer/viz/__init__.py
portformer/viz/_rcparams.py
portformer/viz/main.py
portformer-1.0.1.dist-info/AUTHORS.rst
portformer-1.0.1.dist-info/LICENSE.txt
portformer-1.0.1.dist-info/METADATA
portformer-1.0.1.dist-info/WHEEL
portformer-1.0.1.dist-info/top_level.txt
portformer-1.0.1.dist-info/RECORD
