Metadata-Version: 2.1
Name: portformer
Version: 1.0.1
Summary: Portfolios. Made Better.
Home-page: https://github.com/closedLoop/
Author: Sean Kruzel, Astrocyte Research Inc.
Author-email: skruzel@portformer.com
Maintainer: Sean Kruzel
Maintainer-email: support@portformer.com
License: Astrocyte Research, Inc
Download-URL: https://pypi.python.org/pypi/portformer/1.0.1#downloads
Platform: Windows
Platform: MacOS
Platform: Unix
Classifier: Development Status :: 4 - Beta
Classifier: Intended Audience :: Developers
Classifier: License :: OSI Approved :: Apache Software License
Classifier: Natural Language :: English
Classifier: Operating System :: Microsoft :: Windows
Classifier: Operating System :: MacOS
Classifier: Operating System :: Unix
Classifier: Programming Language :: Python
Classifier: Programming Language :: Python :: 3.4
Classifier: Programming Language :: Python :: 3.5
Classifier: Programming Language :: Python :: 3.6
Classifier: Programming Language :: Python :: 3.7
Classifier: Programming Language :: Python :: 3.8
Requires-Dist: black (==19.10b0)
Requires-Dist: pandas (==1.1.4)
Requires-Dist: pytest (==6.1.2)
Requires-Dist: pytest-cov (==2.10.1)
Requires-Dist: python-dotenv (==0.14.0)
Provides-Extra: docs
Requires-Dist: sphinx (==1.8.1) ; extra == 'docs'
Requires-Dist: sphinx-rtd-theme ; extra == 'docs'
Requires-Dist: sphinx-jinja ; extra == 'docs'
Requires-Dist: sphinx-copybutton ; extra == 'docs'
Requires-Dist: docfly (>=0.0.17) ; extra == 'docs'
Requires-Dist: rstobj (>=0.0.5) ; extra == 'docs'
Requires-Dist: pygments ; extra == 'docs'
Provides-Extra: tests
Requires-Dist: pytest (==3.2.3) ; extra == 'tests'
Requires-Dist: pytest-cov (==2.5.1) ; extra == 'tests'
